hexaviz/__init__.py
hexaviz-1.2.1.dist-info/LICENSE
hexaviz-1.2.1.dist-info/METADATA
hexaviz-1.2.1.dist-info/WHEEL
hexaviz-1.2.1.dist-info/top_level.txt
hexaviz-1.2.1.dist-info/RECORD
